recnetpy/__init__.py
recnetpy/client.py
recnetpy/dataclasses/__init__.py
recnetpy/dataclasses/account.py
recnetpy/dataclasses/base.py
recnetpy/dataclasses/comment.py
recnetpy/dataclasses/event.py
recnetpy/dataclasses/event_response.py
recnetpy/dataclasses/image.py
recnetpy/dataclasses/invention.py
recnetpy/dataclasses/invention_version.py
recnetpy/dataclasses/loading_screen.py
recnetpy/dataclasses/progression.py
recnetpy/dataclasses/promo_external_content.py
recnetpy/dataclasses/role.py
recnetpy/dataclasses/room.py
recnetpy/dataclasses/score.py
recnetpy/dataclasses/subroom.py
recnetpy/dataclasses/tag.py
recnetpy/managers/__init__.py
recnetpy/managers/account_manager.py
recnetpy/managers/base_manager.py
recnetpy/managers/event_manager.py
recnetpy/managers/image_manager.py
recnetpy/managers/invention_manager.py
recnetpy/managers/room_manager.py
recnetpy/misc/__init__.py
recnetpy/misc/api_responses.py
recnetpy/misc/bitmask_decode.py
recnetpy/misc/chunks.py
recnetpy/misc/constants.py
recnetpy/misc/date_to_unix.py
recnetpy/misc/stringify_bulk.py
recnetpy/misc/variable_class.py
recnetpy/rest/__init__.py
recnetpy/rest/http_client.py
recnetpy/rest/request.py
recnetpy/rest/response.py
recnetpy/rest/route_builder.py
recnetpy/rest/route_manager.py
recnetpy/rest/exceptions/__init__.py
recnetpy/rest/exceptions/bad_request.py
recnetpy/rest/exceptions/forbidden.py
recnetpy/rest/exceptions/http_error.py
recnetpy/rest/exceptions/internal_server_error.py
recnetpy/rest/exceptions/not_found.py
recnetpy/rest/exceptions/rate_limited.py
recnetpy/rest/exceptions/unauthorized.py
recnetpy-0.2.75.dist-info/licenses/LICENSE
recnetpy-0.2.75.dist-info/METADATA
recnetpy-0.2.75.dist-info/WHEEL
recnetpy-0.2.75.dist-info/top_level.txt
recnetpy-0.2.75.dist-info/RECORD
