Metadata-Version: 2.4
Name: recnetpy
Version: 0.2.75
Summary: RecNetPy is an API wrapper built in Python for pulling data from RecNet.
Author: RecNetBot Development
Project-URL: Homepage, https://github.com/RecNetBot-Development/RecNetPy
Project-URL: Bug Tracker, https://github.com/RecNetBot-Development/RecNetPy/issues
Classifier: Programming Language :: Python :: 3
Classifier: License :: OSI Approved :: MIT License
Classifier: Operating System :: OS Independent
Requires-Python: >=3.10
License-File: LICENSE
Requires-Dist: aiohttp>=3.8.5
Requires-Dist: python-dateutil==2.8.2
Dynamic: license-file
